ecdsa/__init__.py
ecdsa/_compat.py
ecdsa/_version.py
ecdsa/curves.py
ecdsa/der.py
ecdsa/ecdsa.py
ecdsa/ellipticcurve.py
ecdsa/keys.py
ecdsa/numbertheory.py
ecdsa/rfc6979.py
ecdsa/six.py
ecdsa/test_der.py
ecdsa/test_ecdsa.py
ecdsa/test_ellipticcurve.py
ecdsa/test_keys.py
ecdsa/test_malformed_sigs.py
ecdsa/test_numbertheory.py
ecdsa/test_pyecdsa.py
ecdsa/util.py
ecdsa-0.14.dist-info/LICENSE
ecdsa-0.14.dist-info/METADATA
ecdsa-0.14.dist-info/WHEEL
ecdsa-0.14.dist-info/top_level.txt
ecdsa-0.14.dist-info/RECORD
