Metadata-Version: 2.1
Name: ecdsa
Version: 0.14
Summary: ECDSA cryptographic signature library (pure python)
Home-page: http://github.com/warner/python-ecdsa
Author: Brian Warner
Author-email: warner@lothar.com
License: MIT
Platform: UNKNOWN
Classifier: Programming Language :: Python
Classifier: Programming Language :: Python :: 2
Classifier: Programming Language :: Python :: 2.6
Classifier: Programming Language :: Python :: 2.7
Classifier: Programming Language :: Python :: 3
Classifier: Programming Language :: Python :: 3.3
Classifier: Programming Language :: Python :: 3.4
Classifier: Programming Language :: Python :: 3.5
Classifier: Programming Language :: Python :: 3.6
Classifier: Programming Language :: Python :: 3.7
Classifier: Programming Language :: Python :: 3.8
Requires-Python: >=2.6, !=3.0.*, !=3.1.*, !=3.2.*
Requires-Dist: six
